PyCleanText/PyCleanText.py
PyCleanText/__init__.py
PyCleanText-0.1.0.dist-info/License
PyCleanText-0.1.0.dist-info/METADATA
PyCleanText-0.1.0.dist-info/WHEEL
PyCleanText-0.1.0.dist-info/top_level.txt
PyCleanText-0.1.0.dist-info/RECORD
