Metadata-Version: 2.1
Name: PyCleanText
Version: 0.1.0
Summary: A Python package for cleaning text data by removing noise, stopwords, duplicates, and more.
Author: Md. Ismiel Hossen Abir
Author-email: ismielabir1971@gmail.com
Classifier: Programming Language :: Python :: 3
Classifier: License :: OSI Approved :: MIT License
Classifier: Operating System :: OS Independent
License-File: License
